discord_basic_bridge/__init__.py
discord_basic_bridge-0.1.1.dist-info/LICENSE
discord_basic_bridge-0.1.1.dist-info/WHEEL
discord_basic_bridge-0.1.1.dist-info/METADATA
discord_basic_bridge-0.1.1.dist-info/RECORD
